{
  "dataList": [
    {
      "id": 0,
      "content": "<style=\"den_CP6_1\">Ben... yabani bir canavardan daha alçak bir şey... insan gibi davranmak zorunda mıyım?"
    },
    {
      "id": 1,
      "content": "<style=\"den_CP6_1\">Catherine'i biz öldürdük... yaşamayı hak etmiyoruz."
    },
    {
      "id": 2,
      "content": "<style=\"den_CP6_1\">Kafamın içinde... bir ses duyuyorum..."
    },
    {
      "id": 3,
      "content": "<style=\"den_CP6_1\">Adi, alçak yaratılışım değişemez."
    },
    {
      "id": 4,
      "content": "<style=\"den_CP6_1\">Değişemedim. içi çöp dolu, yırtık pırtık bir çuvalım."
    },
    {
      "id": 5,
      "content": "<style=\"den_CP6_1\">İnsanlar gibi konuşmama gerek yok. Sadece uluyorum."
    },
    {
      "id": 6,
      "content": "<style=\"den_CP6_1\">Cathy, geri geldim... Lütfen..."
    },
    {
      "id": 7,
      "content": "<style=\"den_CP6_1\">Sen ve ben... bir çuvalın içinde... parçalara ayrılmalıyız."
    },
    {
      "id": 8,
      "content": "<style=\"den_CP6_1\">Hepsini sürükleyeceğim... cehennemim derinliklerine."
    }
  ]
}
