{
  "dataList": [
    {
      "id": 0,
      "place": "Unending Hill of Corpses",
      "content": "The fleshy hill exuded potent acid, melting Sinclair's legs.\nAll the Sinners were being dissolved by the caustic secretion."
    },
    {
      "id": 1,
      "content": "Ayağı kayıyor ve yere düşüyor. Hayır, ayakları kesilip yere düşüyor desem daha doğru olur."
    },
    {
      "id": 2,
      "content": "Buna karşın,\nhe still crawls towards Kromer."
    },
    {
      "id": 3,
      "model": "변신크로머",
      "content": "Evet! İşte bu! Canın acıyor, değil mi? İçindeki o öfke dolup taşıyor, değil mi? Kabullen! Bağrına bas o öfkeyi!"
    },
    {
      "id": 4,
      "model": "변신크로머",
      "content": "Ve bana bak! İnsanlığın en saf haline hiç olmadığı kadar yakın olan bu bedene bak! Bu et!\nThe sheer, unmatched strength of purity!"
    },
    {
      "id": 5,
      "model": "변신크로머",
      "content": "Ohh, Sinclair... Kendinin de ne kadar insan olduğuna bak!\nYou can become like me!"
    },
    {
      "id": 6,
      "model": "싱클레어",
      "content": "Ben... Sen..."
    },
    {
      "id": 7,
      "model": "변신크로머",
      "content": "En başından beri korkuyordun, değil mi, Sinclair? Aileni kaybettin, ve yabancılarla birlikte bir otobüse binmek zorunda kalıp, istemediğin şeyleri yapmak zorunda bırakıldın."
    },
    {
      "id": 8,
      "model": "변신크로머",
      "content": "Kalbinin derinliklerinde oraya ait olmadığını biliyordun, değil mi?"
    },
    {
      "id": 9,
      "model": "변신크로머",
      "content": "Kaçmak istemedin mi? Pes etmek istemedin mi? Haksız mıyım?"
    },
    {
      "id": 10,
      "model": "싱클레어",
      "content": "Yemin ediyorum ki, ben..."
    },
    {
      "id": 11,
      "model": "변신크로머",
      "content": "Bana katıl, Sinclair! Kaçma bundan, kabullen!\nComplete my grudge!"
    },
    {
      "id": 12,
      "content": "Sinclair'in silahını tuttuğu kolu her saniye daha da gevşiyordu."
    },
    {
      "id": 13,
      "content": "Yine de Kromer'e doğru yürümeye devam etti."
    },
    {
      "id": 14,
      "model": "변신크로머",
      "content": "Acıyı kabullenmen gerekiyor! Ancak ızdırabın kendisini aşar isek yeniden doğabiliriz!"
    },
    {
      "id": 15,
      "model": "변신크로머",
      "content": "Eti şişir, kanı dök! Her saniye daha insani şeyleri...!"
    },
    {
      "id": 16,
      "model": "변신크로머",
      "content": "İşe tüm insanların şehrinin sarıldığı kirliliğin süzerek ayrılılacağı o dünyaya ekle!"
    },
    {
      "id": 17,
      "model": "싱클레어",
      "content": "Anne... Baba... Abla..."
    },
    {
      "id": 18,
      "content": "Ölmüş Günahkar dostlarının yüzlerine bakarak, Sinclair dalgın bir şekilde mırıldandı."
    },
    {
      "id": 19,
      "content": "Onu öyle bırakamazdım."
    },
    {
      "id": 20,
      "model": "단테",
      "content": "<Sinclair! Beni dinle!>"
    },
    {
      "id": 21,
      "content": "Harekete geçmemin bu kadar uzun sürmesi beni utandırıyordu, ama geç olması hiç olmamasından daha iyiydi."
    },
    {
      "id": 22,
      "content": "Olduğum müdür gibi davranmam."
    },
    {
      "id": 23,
      "model": "단테",
      "content": "<Çok aklına sığındığını biliyordum! O kafandan diğer kişilere söyleyemeceğin çok şeyin geçtiğini biliyorum!>"
    },
    {
      "id": 24,
      "content": "Sinclair öyle birisiydi."
    },
    {
      "id": 25,
      "content": "Bir yük olabileceği korkusuyla, zihnini, çoğuna geçit izin vermediği düşünceler ile meşgul ederdi."
    },
    {
      "id": 26,
      "content": "Birçok düşünceyi suçluluk düşüncesiyle çiğnerdi."
    },
    {
      "id": 27,
      "model": "싱클레어",
      "content": "Ailem benim yüzümden öldü..."
    },
    {
      "id": 28,
      "model": "싱클레어",
      "content": "Söylememem gerekn şeyler söyledim..."
    },
    {
      "id": 29,
      "model": "변신크로머",
      "content": "Evet! Evet, hepsi senin suçun, bu yüzden kabullen! Bir bütün olmanın yolu bu!"
    },
    {
      "id": 30,
      "model": "변신크로머",
      "content": "Benim yolumdan git... Ve benim ellerimde dinlen!"
    },
    {
      "id": 31,
      "model": "단테",
      "content": "<Sakın onu dinleme!>"
    },
    {
      "id": 32,
      "model": "단테",
      "content": "<You have to see! Look at her, observe her carefully!>"
    },
    {
      "id": 33,
      "content": "Fakat, sesim ona ulaşmamış gibi görünüyordu."
    },
    {
      "id": 34,
      "model": "싱클레어",
      "content": "Ah..."
    },
    {
      "id": 35,
      "content": "Sinclair'in silahı elinden düşüp yere çarptı."
    },
    {
      "id": 36,
      "content": "İlerleyişi durdu."
    },
    {
      "id": 37,
      "content": "Evet, görünüyor ki bu bizim için bir son."
    },
    {
      "id": 38,
      "content": "Vücudumun, tepeye doğru eridiğini hissedebiliyorum."
    },
    {
      "id": 39,
      "content": "Er ya da geç patronluk rolü yapmaya çalışırken öleceğimi biliyordum.."
    },
    {
      "id": 40,
      "content": "Ama..."
    },
    {
      "id": 41,
      "model": "단테",
      "content": "<Sinclair…>"
    },
    {
      "id": 42,
      "content": "Ona daha çok şey söylemek zorundaydım."
    },
    {
      "id": 43,
      "content": "Kromer'in söylediklerinin bir yığın yalan, göz korkutma, ikiyüzlülük ve abartıdan ibaret olduğunu ona söylemek zorundaydım."
    },
    {
      "id": 44,
      "content": "Vücudumdaki tüm sinirler bana ondan vazgeçmemem gerektiğini haykırıyordu"
    },
    {
      "id": 45,
      "content": "Eriyen vücudumun yanma acısını hissederek..."
    },
    {
      "id": 46,
      "model": "단테",
      "content": "<İyi, iyi bak! Sinclair!>"
    },
    {
      "id": 47,
      "model": "단테",
      "content": "<Gözlerinle değil, kalbinle!>"
    },
    {
      "id": 48,
      "content": "Sinclair'e bağırdım."
    },
    {
      "id": 49,
      "model": "단테",
      "content": "<Ancak o zaman… en önemli şeyi görebilirsin>"
    },
    {
      "id": 50,
      "teller": "???",
      "title": "???",
      "content": "Ancak o zaman, en önemli şeyi görebilirsin."
    },
    {
      "id": 51,
      "content": "Tam o anda..."
    },
    {
      "id": 52,
      "content": "Birisi sessizce belirdi."
    },
    {
      "id": 53,
      "model": "데미안",
      "teller": "???",
      "title": "???",
      "content": "And when you can see the thing that matters the most..."
    },
    {
      "id": 54,
      "model": "데미안",
      "teller": "???",
      "title": "???",
      "content": "You won't have to stifle yourself with shallow threats or cheap tricks."
    },
    {
      "id": 55,
      "model": "데미안",
      "teller": "???",
      "title": "???",
      "content": "...Haksız mıyım, Sinclair?"
    },
    {
      "id": -1,
      "content": "인게임으로 씬전환"
    },
    {
      "id": 56,
      "content": "He moved with grace and airiness, as though he floated in the air."
    },
    {
      "id": 57,
      "content": "He seemed lighter than anyone else, unbound by anything."
    },
    {
      "id": 58,
      "content": "Contrary to his impression of freedom from all worldly longings, an oppressive air seemed to accompany every step he took."
    },
    {
      "id": 59,
      "content": "Ve sol elini salladığında..."
    },
    {
      "id": -1,
      "content": "크로머 싹둑"
    },
    {
      "id": 60,
      "content": "Kromer'ın bedeninin üst kısmı pürüzsüz bir şekilde kesilip atıldı."
    }
  ]
}
