{
    "dataList": [
        {
            "id": 0,
            "place": "Eunbong’un Barı ve Kızartmacısı",
            "model": "은봉치킨",
            "teller": "Eunbong’un Barı ve Kızartmacısı'nın Sahibi",
            "title": "Eunbong’un Barı ve Kızartmacısı",
            "content": "…Bu tavuk lokantasını işletirken önemli bir şeyi unutmuşum…"
        },
        {
            "id": 1,
            "model": "은봉치킨",
            "teller": "Eunbong’un Barı ve Kızartmacısı'nın Sahibi",
            "title": "Eunbong’un Barı ve Kızartmacısı",
            "content": "Evet, pişirmek istediğim tavuk…"
        },
        {
            "id": 2,
            "model": "은봉치킨",
            "teller": "Eunbong’un Barı ve Kızartmacısı'nın Sahibi",
            "title": "Eunbong’un Barı ve Kızartmacısı",
            "content": "…Annemin bile zevkle yiyebileceği bir yemekti."
        },
        {
            "id": 3,
            "model": "은봉치킨",
            "teller": "Eunbong’un Barı ve Kızartmacısı'nın Sahibi",
            "title": "Eunbong’un Barı ve Kızartmacısı",
            "content": "Onun son derece özel damak zevkini memnun edecek bir şey…"
        },
        {
            "id": 4,
            "model": "은봉치킨",
            "teller": "Eunbong’un Barı ve Kızartmacısı'nın Sahibi",
            "title": "Eunbong’un Barı ve Kızartmacısı",
            "content": "……"
        },
        {
            "id": 5,
            "model": "은봉치킨",
            "teller": "Eunbong’un Barı ve Kızartmacısı'nın Sahibi",
            "title": "Eunbong’un Barı ve Kızartmacısı",
            "content": "Hayır, bekle…"
        },
        {
            "id": 6,
            "model": "은봉치킨",
            "teller": "Eunbong’un Barı ve Kızartmacısı'nın Sahibi",
            "title": "Eunbong’un Barı ve Kızartmacısı",
            "content": "Bunu en başından beri biliyordum."
        },
        {
            "id": 7,
            "model": "은봉치킨",
            "teller": "Eunbong’un Barı ve Kızartmacısı'nın Sahibi",
            "title": "Eunbong’un Barı ve Kızartmacısı",
            "content": "Annemin tavuk yememesinin gerçek nedeni…"
        },
        {
            "id": 8,
            "model": "은봉치킨",
            "teller": "Eunbong’un Barı ve Kızartmacısı'nın Sahibi",
            "title": "Eunbong’un Barı ve Kızartmacısı",
            "content": "…tüm aileyi doyuracak paramızın olmamasıydı.…"
        },
        {
            "id": 9,
            "model": "은봉치킨",
            "teller": "Eunbong’un Barı ve Kızartmacısı'nın Sahibi",
            "title": "Eunbong’un Barı ve Kızartmacısı",
            "content": "İşte bu yüzden… evde her zaman bir kupon stoğumuz vardı… Bunlardan on tanesi bedava tavukla değiştirilebilirdi…"
        },
        {
            "id": 10,
            "model": "은봉치킨",
            "teller": "Eunbong’un Barı ve Kızartmacısı'nın Sahibi",
            "title": "Eunbong’un Barı ve Kızartmacısı",
            "content": "Annem onları benim için toplamaya devam ederdi.…"
        },
        {
            "id": 11,
            "model": "은봉치킨",
            "teller": "Eunbong’un Barı ve Kızartmacısı'nın Sahibi",
            "title": "Eunbong’un Barı ve Kızartmacısı",
            "content": "Bana yemeyeceğin bir tavuğu yedirmek için bütün bunları yaptın…"
        },
        {
            "id": 12,
            "model": "은봉치킨",
            "teller": "Eunbong’un Barı ve Kızartmacısı'nın Sahibi",
            "title": "Eunbong’un Barı ve Kızartmacısı",
            "content": "……"
        },
        {
            "id": 13,
            "model": "은봉치킨",
            "teller": "Eunbong’un Barı ve Kızartmacısı'nın Sahibi",
            "title": "Eunbong’un Barı ve Kızartmacısı",
            "content": "Hm?"
        },
        {
            "id": 14,
            "model": "은봉치킨",
            "teller": "Eunbong’un Barı ve Kızartmacısı'nın Sahibi",
            "title": "Eunbong’un Barı ve Kızartmacısı",
            "content": "Ah."
        },
        {
            "id": 15,
            "model": "은봉치킨",
            "teller": "Eunbong’un Barı ve Kızartmacısı'nın Sahibi",
            "title": "Eunbong’un Barı ve Kızartmacısı",
            "content": "Bunlar pizza kuponları."
        },
        {
            "id": 16,
            "teller": "Restoran Sahibi'nin Annesi",
            "title": "Eunbong’un Barı ve Kızartmacısı",
            "content": "Oğlum, annen…"
        },
        {
            "id": 17,
            "teller": "Restoran Sahibi'nin Annesi",
            "title": "Eunbong’un Barı ve Kızartmacısı",
            "content": "O… pizzayı daha çok seviyordu…"
        },
        {
            "id": 18,
            "model": "은봉치킨",
            "teller": "Eunbong’un Barı ve Kızartmacısı'nın Sahibi",
            "title": "Eunbong’un Barı ve Kızartmacısı",
            "content": "Agh… Başım…"
        },
        {
            "id": 19,
            "model": "단테",
            "content": "<Normal haline döndü.>"
        },
        {
            "id": 20,
            "model": "오티스",
            "content": "Bu iyi bir plandı. Havuç ve sopa yaklaşımı. Askeri operasyonlarda sıklıkla kullanılan etkili bir taktiktir."
        },
        {
            "id": 21,
            "model": "이스마엘",
            "content": "Bu… bir plan mıydı? Bunun her zamanki bağırıp çağırmandan ve ilk saldırma taktiğinden bir farkı olduğunu göremiyorum…"
        },
        {
            "id": 22,
            "model": "오티스",
            "content": "Çok ince bir hareketti ve bu yakışıklı genç ipucumu yakaladı ve hemen takip etti."
        },
        {
            "id": 23,
            "model": "싱클레어",
            "content": "T—Teşekkürler, Kaptan Outis!"
        },
        {
            "id": 24,
            "model": "단테",
            "content": "<Outis'e az kalsın “çaylak” diyecektin, değil mi?>"
        },
        {
            "id": 25,
            "model": "은봉치킨",
            "teller": "Eunbong’un Barı ve Kızartmacısı'nın Sahibi",
            "title": "Eunbong’un Barı ve Kızartmacısı",
            "content": "Size ne kadar teşekkür etsem az. Sanırım yeniden başlamaya hazırım."
        },
        {
            "id": 26,
            "model": "은봉치킨",
            "teller": "Eunbong’un Barı ve Kızartmacısı'nın Sahibi",
            "title": "Eunbong’un Barı ve Kızartmacısı",
            "content": "İhtiyacım olan tarif bu değildi… Sevdiğim kişiler için gönülden yemek yapmayı hatırladığım sürece Pizza şeklinde bile olsa… Müşterilerimin sevgiyle yapılan yemekleri takdir edeceklerini biliyorum."
        },
        {
            "id": 27,
            "model": "히스클리프",
            "content": "Hey, rakibin bize bedava tavuk için ömür boyu kefil sözü verdi. Peki ya sende ne var?"
        },
        {
            "id": 28,
            "model": "로쟈",
            "content": "Ben… şimdiye kadar sayısız lezzetli bagetlerle ağzımı dolduracağımı sanıyordum…"
        },
        {
            "id": 29,
            "model": "은봉치킨",
            "teller": "Eunbong’un Barı ve Kızartmacısı'nın Sahibi",
            "title": "Eunbong’un Barı ve Kızartmacısı",
            "content": "……"
        },
        {
            "id": 30,
            "model": "은봉치킨",
            "teller": "Eunbong’un Barı ve Kızartmacısı'nın Sahibi",
            "title": "Eunbong’un Barı ve Kızartmacısı",
            "content": "Çok fazla değil, ama lütfen bunu alın…"
        },
        {
            "id": 31,
            "content": "Eunbong’un sahibi bize paketlenmiş bir kutu verdi."
        },
        {
            "id": 32,
            "model": "은봉치킨",
            "teller": "Eunbong’un Barı ve Kızartmacısı'nın Sahibi",
            "title": "Eunbong’un Barı ve Kızartmacısı",
            "content": "Benim için paha biçilmez bir hazine, buna benzer başka hiçbir şey yok…"
        },
        {
            "id": 33,
            "model": "돈키호테",
            "content": "Senden böyle bir nadideliği kabul edebilir miyiz?"
        },
        {
            "id": 34,
            "model": "은봉치킨",
            "teller": "Eunbong’un Barı ve Kızartmacısı'nın Sahibi",
            "title": "Eunbong’un Barı ve Kızartmacısı",
            "content": "Sizin yardımınız olmasaydı restoranımı yeniden açamazdım… Bu yüzden ısrar ediyorum, lütfen bunu ödül olarak kabul edin."
        },
        {
            "id": 35,
            "place": "Mephistopheles'in Dışarısı",
            "model": "돈키호테",
            "content": "…Ve böylece Bozuklu'ğu çözmüş ve ganimetlerimizi toplamış olduk!"
        },
        {
            "id": 36,
            "model": "베르길리우스",
            "content": "……"
        },
        {
            "id": 37,
            "model": "돈키호테",
            "content": "Lütfen anlatın, lütfen anlatın! Hikayemizin ihtişamı karşısında hayretten diliniz mi tutuluyor?!"
        },
        {
            "id": 38,
            "model": "베르길리우스",
            "content": "“Daha sonra Eunbong'a doğru yola koyulduk” derken sesim kısıldı."
        },
        {
            "id": 39,
            "model": "돈키호테",
            "content": "Demek ki hiçbir şey duymamışsın!"
        },
        {
            "id": 40,
            "model": "베르길리우스",
            "content": "Faust'un raporu bana ihtiyacım olan tüm ayrıntıları verecekken, neden senin abartılı saçmalıklarını dinleyeyim ki?"
        },
        {
            "id": 41,
            "model": "로쟈",
            "content": "Hadi ama, Donqui. Bu asık suratlıyı unut ve etrafımıza toplan ki kutuyu açabilelim. Heeheehee."
        },
        {
            "id": 42,
            "model": "로쟈",
            "content": "Acaba içinde ne var~"
        },
        {
            "id": 43,
            "content": "Etrafında günahkarlar toplanmış, beklentiyle doluyken, kapak açıldı…"
        },
        {
            "id": 44,
            "model": "은봉치킨",
            "teller": "Eunbong’un Barı ve Kızartmacısı'nın Sahibi",
            "title": "Eunbong’un Barı ve Kızartmacısı",
            "content": "“Maskotumuzun tek ve biricik bebeği Bongy ile tanışın. Bir gün kullanılacağını umarak yaptım ama minnettarlığımın bir hediyesi olarak vermekten mutluluk duyuyorum. ^0^/”"
        },
        {
            "id": 45,
            "model": "로쟈",
            "content": "İmkanı yok… Belki peluşun karnına bir şey saklamıştır?"
        },
        {
            "id": 46,
            "model": "단테",
            "content": "<Bunu yapacak biri gibi görünmüyor…>"
        },
        {
            "id": 47,
            "model": "그레고르",
            "content": "Muhtemelen ondan kurtulmaya çalışıyordu ve biz de onu almak için oradaydık, ha?"
        },
        {
            "id": 48,
            "model": "히스클리프",
            "content": "Şunu şu yakma fırınına atalım."
        },
        {
            "id": 49,
            "content": "Bir el, Heathcliff'in vahşi bir öfkeyle kavradığı bebeği nazikçe çekiştirdi."
        },
        {
            "id": 50,
            "model": "카론",
            "content": "Charon bu yolcuyu sevdi."
        },
        {
            "id": 51,
            "model": "히스클리프",
            "content": "Bu oyuncağın sevilecek neyi var—"
        },
        {
            "id": 52,
            "model": "카론",
            "content": "Sadece gözleri var, başka da bir şeyi yok."
        },
        {
            "id": 53,
            "model": "카론",
            "content": "Çok güzel."
        },
        {
            "id": 54,
            "model": "베르길리우스",
            "content": "…Tamam. Peki öyleyse. Bebek senin olsun."
        },
        {
            "id": 55,
            "model": "뫼르소",
            "content": "Bu yanlış bir değerlendirmeydi çünkü bebeğin bir gövdesi ve uzuvları vardı."
        },
        {
            "id": 56,
            "content": "İşte böyle, ömür boyu bedava yemek yerine aldığımız tavuk peluşu otobüste yerini aldı…"
        },
        {
            "id": 57,
            "model": "삼조",
            "teller": "Samjo",
            "title": "K Kurulu Gıda Kaynaklarının Geliştirilmesi Departmanı?",
            "content": "Evet, Şef Dongrang. Bozukluk çözüldü. Bunu kendi gözlerimle doğruladım."
        },
        {
            "id": 58,
            "place": "Bodhisattva Chicken",
            "model": "삼조",
            "teller": "Samjo",
            "title": "K Kurulu Gıda Kaynaklarının Geliştirilmesi Departmanı?",
            "content": "İlk başta biraz güvenilmez görünüyorlardı, evet… Ama onlarla konuşmanın sorun olmayacağını düşünüyorum. Evet, onları şimdi getireceğim."
        },
        {
            "id": 59,
            "model": "보살치킨",
            "teller": "Bodhisattva Tavukçusu'nun Müdürü",
            "title": "Bodhisattva Tavukçusu",
            "content": "Ş—Şimdi ne olacak?"
        },
        {
            "id": 60,
            "model": "삼조",
            "teller": "Samjo",
            "title": "K Kurulu Gıda Kaynaklarının Geliştirilmesi Departmanı?",
            "content": "Ben… öznesi olmayan cümlelerden hoşlanmam."
        },
        {
            "id": 61,
            "model": "보살치킨",
            "teller": "Bodhisattva Tavukçusu'nun Müdürü",
            "title": "Bodhisattva Tavukçusu",
            "content": "O restoran tekrar açıldığında müşterilerimizi kaybedeceğiz… O zaman kotayı kaçıracağım ve…"
        },
        {
            "id": 62,
            "model": "삼조",
            "teller": "Samjo",
            "title": "K Kurulu Gıda Kaynaklarının Geliştirilmesi Departmanı?",
            "content": "Çalınan tarifi bir konsept yakma fırınına koyduğun andan itibaren bir yaşam yolu aramaya başlaman gerekirdi."
        },
        {
            "id": 63,
            "model": "삼조",
            "teller": "Samjo",
            "title": "K Kurulu Gıda Kaynaklarının Geliştirilmesi Departmanı?",
            "content": "“Bir evi soyduğunuzda, ev sahibinin bunu asla fark etmemesine dikkat edin” sözünü hiç duymadınız mı?"
        },
        {
            "id": 64,
            "model": "보살치킨",
            "teller": "Bodhisattva Tavukçusu'nun Müdürü",
            "title": "Bodhisattva Tavukçusu",
            "content": "Ben… Ben hiçbir şey bilmiyorum… Ben…"
        },
        {
            "id": 65,
            "model": "삼조",
            "teller": "Samjo",
            "title": "K Kurulu Gıda Kaynaklarının Geliştirilmesi Departmanı?",
            "content": "Evet, tabi ki hatırlamadın; bunu şimdi uydurdum. Bir dahaki sefere iyi hatırlayın."
        },
        {
            "id": 66,
            "model": "삼조",
            "teller": "Samjo",
            "title": "K Kurulu Gıda Kaynaklarının Geliştirilmesi Departmanı?",
            "content": "Görüşürüz."
        },
        {
            "id": 67,
            "model": "삼조",
            "teller": "Samjo",
            "title": "K Kurulu Gıda Kaynaklarının Geliştirilmesi Departmanı?",
            "content": "Selamlanmaya ihtiyacı olan ziyaretçilerim var."
        },
        {
            "id": 68,
            "content": "Ve çok geçmeden, eşi benzeri görülmemiş ölçekte bir karmaşanın içine sürüklendik…"
        }
    ]
}
