{
    "dataList": [
        {
            "id": 0,
            "place": "Nest K’s Streets",
            "model": "파우스트",
            "content": "Otobüsün içinden de gördüğümüz üzere… Bir Yuvanın tam ortasındayız. Beklenmedik sorunlarla karşılaşabilecek son yerlerden birinde."
        },
        {
            "id": 1,
            "model": "홍루",
            "content": "Hmm… Yani bu yaşananlar değerli anlar mı?"
        },
        {
            "id": 2,
            "content": "Everyone except drowsy Hong Lu was tensed up, carefully observing what was going on…"
        },
        {
            "id": 3,
            "model": "단테",
            "content": "<Hm? Is that…>"
        },
        {
            "id": 4,
            "content": "Someone was running our way in a hurry from the other side."
        },
        {
            "id": 5,
            "content": "The civilian was too hurried to look ahead; they bumped into the Sinners and fell to the ground."
        },
        {
            "id": 6,
            "model": "도망치던시민",
            "teller": "Running Civilian",
            "title": "Nest K",
            "content": "Huff, huff… O-O Tarafa sakın gitmeyin!"
        },
        {
            "id": 7,
            "model": "돈키호테",
            "content": "Come now, you may rest easy! We have galloped hither to save innocent lives such as yours for we are—"
        },
        {
            "id": 8,
            "model": "이스마엘",
            "content": "Bizler kahraman falan değiliz, lütfen böylesine gereksiz şeyler söyleme."
        },
        {
            "id": 9,
            "model": "히스클리프",
            "content": "Karşıya geçmemiz lazım lan. Eğer bizi önemli bir şey için durdurmuyorsan, bu sopayı götüne sokarım senin."
        },
        {
            "id": 10,
            "content": "Heathcliff'in korkutucu bakışları, ve Ishmael'in öfkeli sözleri arasında sivil, ikisinden hangisinin daha çok tehdit teşkil ettiğini sorgulamıştı bir an."
        },
        {
            "id": 11,
            "model": "도망치던시민",
            "teller": "Running Civilian",
            "title": "Nest K",
            "content": "İleride… gerçek olmaması… gereken bir şey var…"
        },
        {
            "id": 12,
            "model": "도망치던시민",
            "teller": "Running Civilian",
            "title": "Nest K",
            "content": "Ne olduğunu bilmiyorum, hayatımda böyle bir şey görmedim… Herkes bağırışıp çağırışıp kaçıyordu, ve… yerlerde yuvarlanıyorlardı… çoktan kül olmuş halde…"
        },
        {
            "id": 13,
            "model": "뫼르소",
            "content": "Karşılaştığınız varlık, yapısal olarak bir insana benzetilemiyor mu?"
        },
        {
            "id": 14,
            "model": "도망치던시민",
            "teller": "Running Civilian",
            "title": "Nest K",
            "content": "…Evet, haklısınız, çok haklısınız…!"
        },
        {
            "id": 15,
            "model": "이스마엘",
            "content": "Yani, bu bir insan değilse…"
        },
        {
            "id": 16,
            "content": "Keeping the suspected possibilities in our minds, we headed for the center of the disturbance…"
        },
        {
            "id": 17,
            "place": "Nest K’s Ruined Streets",
            "model": "싱클레어",
            "content": "N-Neler oluyor burada?"
        },
        {
            "id": 18,
            "model": "히스클리프",
            "content": "Bu şey değil mi ya… Bozukluk falandır belki lan, şu tavukçu herif gibi?"
        },
        {
            "id": 19,
            "model": "단테",
            "content": "<No… That’s different… That one is an Abnormality, not a Distortion. I’m sure of this… somehow.>"
        },
        {
            "id": 20,
            "model": "파우스트",
            "content": "As Dante suggested, that entity is likely to be an Abnormality. Our manager is able to “sense” it."
        },
        {
            "id": 21,
            "model": "단테",
            "content": "<But then, why…>"
        },
        {
            "id": 22,
            "model": "단테",
            "content": "<Why is an Abnormality in the middle of a Nest?>"
        },
        {
            "id": 23,
            "model": "파우스트",
            "content": "Bu Faust'un bilgilendirilmediği bir fenomen. Çoğu Lobotomi Kuruluşu dalı, Kanat dağıldıktan hemen sonra kapartıldı."
        },
        {
            "id": 24,
            "content": "I was reminded of the site burial Yuri told us about, but I quickly shook off those gloomy memories."
        },
        {
            "id": 25,
            "model": "파우스트",
            "content": "Bir Anomali bu esnada firar etmiş olsa dahi, bu görevden önce bize böyle bir olayın bilgisi muhakkak olaşırdı."
        },
        {
            "id": 26,
            "model": "파우스트",
            "content": "Böyle bir olayın yaşanmasının ardından LŞT'nin bu konuda haber alamama ihtimali, kulağa oldukça güç geliyor."
        },
        {
            "id": 27,
            "model": "싱클레어",
            "content": "…Belki de K Kuruluşu tarafından gönderilen güvenlik görevlilerindendir?"
        },
        {
            "id": 28,
            "model": "이스마엘",
            "content": "Anomali'yi bastırmayı bırak… ağız burun etrafa dağılıyorlar."
        },
        {
            "id": 29,
            "model": "그레고르",
            "content": "Mmh… D Kuruluşu'nun eyaletinde sağlam dayak yediğimiz günleri hatırlatıyor…"
        },
        {
            "id": 30,
            "model": "로쟈",
            "content": "Aw, hadi be~ Önce şu tavukçu herifin götü başı ayrı oynuyor, şimdi de bunun m u? Gerçekten de harika bir karşılama…"
        },
        {
            "id": 31,
            "content": "Right as they complained…"
        },
        {
            "id": 32,
            "model": "히스클리프",
            "content": "Gah! Hassiktir lan…"
        },
        {
            "id": 33,
            "content": "Debris created by the rampaging Abnormality narrowly grazed past us."
        },
        {
            "id": 34,
            "model": "히스클리프",
            "content": "Hah, napıyoruz lan biz? Mevzuyu buradan top gibi izlemenin kimseye yararı yok!"
        },
        {
            "id": 35,
            "model": "히스클리프",
            "content": "…Bizi paspas edecek amına koyayim."
        },
        {
            "id": 36,
            "model": "오티스",
            "content": "……"
        },
        {
            "id": 37,
            "model": "오티스",
            "content": "Çok yanılıyorsun. O deli veletin saçma sözleri sonunda senin de mi beynini yıkadı?"
        },
        {
            "id": 38,
            "model": "돈키호테",
            "content": "Ho, hark? I prithee, who dost thou mean by this “insane brat”?"
        },
        {
            "id": 39,
            "model": "오티스",
            "content": "Rehber bize sadece sorun çözüldüğünde dönmemiz emrini verdi. Sorunu bizim çözmemiz gerektiğini emretmedi."
        },
        {
            "id": 40,
            "model": "히스클리프",
            "content": "Allah rızası için, bu kadar kalın kafalı olacak ne var lan?"
        },
        {
            "id": 41,
            "model": "히스클리프",
            "content": "Ne yaşandığını görmüyor musunuz oğlum? Kellem gidiyordu amına koyayim! Eğer böyle devam ederse kim bilir neler edecek bize!"
        },
        {
            "id": 42,
            "model": "히스클리프",
            "content": "Şu bronzunu siktiğimin boğasını öldürsek bitecek ya her şey… Ne bekliyoruz? Banka oturup şu elemanın tavukları mideye mi indireceğiz lan?!"
        },
        {
            "id": 43,
            "model": "오티스",
            "content": "Görevimizle alakasız bir şey ile savaşıp, canımızı harcamamız oldukça gereksiz."
        },
        {
            "id": 44,
            "model": "오티스",
            "content": "Siz pislikler elbet anlamamışsınızdır, ama olay şu ki…"
        },
        {
            "id": 45,
            "model": "오티스",
            "content": "Ne kadar ölürseniz, savaşta o kadar verimsiz kalırsınız."
        },
        {
            "id": 46,
            "model": "오티스",
            "content": "Acıyı deneyimlemek, korkmanızı sağlayıp sizin hareketlerinizi kısıtlar."
        },
        {
            "id": 47,
            "model": "뫼르소",
            "content": "……"
        },
        {
            "id": 48,
            "model": "싱클레어",
            "content": "…Biz burada kavga ederken, millet hala can çekişiyor ama?"
        },
        {
            "id": 49,
            "model": "오티스",
            "content": "Biraz zaman alacak olsa ve bir çok can kaybı olsa dahi… eninde sonunda bastıracaklar. Tıpkı bizim yapacağımız gibi."
        },
        {
            "id": 50,
            "model": "오티스",
            "content": "Ve demeliyim ki… Her ölüm öncesi ailesi için göz yaşları döken amatör bir veletten, canımızı feda etmemizi istemesini beklemezdim.."
        },
        {
            "id": 51,
            "model": "오티스",
            "content": "Ölüm artık senin için bir hiç, değil mi?"
        },
        {
            "id": 52,
            "model": "싱클레어",
            "content": "……"
        },
        {
            "id": 53,
            "model": "뫼르소",
            "content": "Eğer Günahkarlar arasında verilebilecek en iyi kararı almak istiyorsak, onu dinlememiz doğru olandır."
        },
        {
            "id": 54,
            "model": "단테",
            "content": "<I…>"
        },
        {
            "id": 55,
            "content": "We’re not Fixers, and we certainly cannot be heroes."
        },
        {
            "id": 56,
            "content": "Turning the clock obviously hurts whenever I do it, and the pain is something I can never get used to."
        },
        {
            "id": 57,
            "content": "And yet…"
        },
        {
            "id": 58,
            "model": "단테",
            "content": "<We should suppress it. I can’t logically explain why, but… I feel like we should.>"
        },
        {
            "id": 59,
            "model": "오티스",
            "content": "……"
        },
        {
            "id": 60,
            "model": "히스클리프",
            "content": "Eğer onlarla aynı boku söyleseydin, yarrağımdan küçük yelkovanlı kafanı püreye çevirip oraya fırlardım, saat kafa."
        },
        {
            "id": 61,
            "model": "뫼르소",
            "content": "Eğer kararınız buysa, buna uyacağım."
        },
        {
            "id": 62,
            "model": "그레고르",
            "content": "Evet, pekalaaa… Doğru kararı verdiğinize eminim."
        },
        {
            "id": 63,
            "model": "싱클레어",
            "content": "Hey, ah… Verdiğiniz karar için teşekkür ederim."
        },
        {
            "id": 64,
            "model": "료슈",
            "content": "Küçük şeylere fazla endişeleniyorsun, saat. Senden sanatçı olmaz."
        },
        {
            "id": 65,
            "model": "오티스",
            "content": "…Bu kadar siz, yani İdari Müdürümüzden başka kimsece kararlaştırılmadı."
        },
        {
            "id": 66,
            "content": "The Sinners walk ahead after leaving me comments."
        },
        {
            "id": 67,
            "content": "While all the others moved forward, Faust remained and gave me a peculiar stare."
        },
        {
            "id": 68,
            "model": "단테",
            "content": "<What is it? You think my judgement was inefficient?>"
        },
        {
            "id": 69,
            "model": "파우스트",
            "content": "Hayır, Sadece hafızanı geri aldığında yüzünün alacağı tepkiyi görmenin ilginç olacağını düşünüyordum."
        },
        {
            "id": 70,
            "content": "Faust’s strange statement held me in place for a moment, but I decided I want to deal with the questions that are immediately ahead of me first."
        },
        {
            "id": 71,
            "model": "단테",
            "content": "<Faust, I’ve been wondering for a while… Are you really okay with being treated like this, considering your talent and everything?>"
        },
        {
            "id": 72,
            "content": "Someone of her caliber should have no problem enjoying a luxurious life in the City."
        },
        {
            "id": 73,
            "model": "파우스트",
            "content": "Faust'un pek ilgisini çekmiyor. Yanı sıra, “yetenek”, Faust'u açıklamak için doğru bir kelime değil."
        },
        {
            "id": 74,
            "model": "파우스트",
            "content": "Bir çok kişi yetenekli olabilir, fakat Faust bu bir çok kişiden birisi olmak istemiyor."
        },
        {
            "id": 75,
            "model": "파우스트",
            "content": "Günahkarlar arasında, en yaygın kullanılan tabire göre yetenekli birisini söyleyecek olursak, bu kişi… Yi Sang olurdu. Bilin ki, ben bir dahiyim."
        },
        {
            "id": 76,
            "content": "Yi Sang stops walking behind the other Sinners and turns around to face me."
        },
        {
            "id": 77,
            "content": "Looking again, his eyes actually stare into the emptiness behind me."
        },
        {
            "id": 78,
            "model": "이상",
            "content": "…Ben öyle bir güruh değilim."
        },
        {
            "id": 79,
            "model": "이상",
            "content": "Evvel zamandan beridir, kanatlarımı çırpmayı bıraktım."
        },
        {
            "id": 80,
            "model": "이상",
            "content": "Yani, yeteneklerimi konuşmak nafiledir, Müdür."
        },
        {
            "id": 81,
            "model": "단테",
            "content": "<……>"
        },
        {
            "id": 82,
            "content": "Curiously enough, I find that some Sinners feel more distant as we spend more time together."
        },
        {
            "id": 83,
            "model": "료슈",
            "content": "Şu uçan makine ne? Sinirimi bozuyor. A.Y.K'mi getirtiyor. üç bininci kez."
        },
        {
            "id": 84,
            "model": "이상",
            "content": "O… Dron denen bir cihaz."
        },
        {
            "id": 85,
            "model": "이스마엘",
            "content": "Oh, Bize yardıma gelen K Kuruluşu savaş dronlarından olabilirler. Kanat, teknoloji konusunda pek bir üstün görünüyor."
        },
        {
            "id": 86,
            "model": "파우스트",
            "content": "Hayır. Dizaynına bakacak olursak, savaş kabiliyetleri ile donatılmışa benzemiyorlar. Ayrıca ortalarında bir kamera var."
        },
        {
            "id": 87,
            "model": "이스마엘",
            "content": "Yani… Güzel mi güzel bir Yuva'nın içinde böylesine bir olay yaşanırken, biraz yakından bakmak pek bir mantıklı."
        },
        {
            "id": 88,
            "content": "Abashed, Ishmael mumbled."
        },
        {
            "id": 89,
            "model": "돈키호테",
            "content": "Ohh! Will we be featured on the thing called the “news”?"
        },
        {
            "id": 90,
            "model": "싱클레어",
            "content": "Bekle, bir sorun var… Neden…"
        },
        {
            "id": 91,
            "model": "싱클레어",
            "content": "Neden sadece cesetleri ve yaralıları çekiyorlar?"
        },
        {
            "id": 92,
            "model": "그레고르",
            "content": "Provokatif şeyler ekran başına daha çok kişiyi yapıştırır, değil mi?"
        },
        {
            "id": 93,
            "model": "로쟈",
            "content": "“Şu korkunç kazaya da bakın! Ne kadar da vahşi!” falan filan işte."
        },
        {
            "id": 94,
            "model": "싱클레어",
            "content": "Ama…"
        },
        {
            "id": 95,
            "model": "로쟈",
            "content": "Dur, çocuk! Hemen önünde!"
        },
        {
            "id": 96,
            "model": "싱클레어",
            "content": "Kngh… Bu… kesinlikle çok garip…"
        },
        {
            "id": 97,
            "model": "단테",
            "content": "<Sinclair!>"
        },
        {
            "id": 98,
            "model": "싱클레어",
            "content": "Şuna da bir bakın. Neden kamerası bana kitlendi…?"
        },
        {
            "id": 99,
            "model": "료슈",
            "content": "…Ruhsuz izleyicilerden hiç hoşlanmam."
        },
        {
            "id": 100,
            "model": "뫼르소",
            "content": "Bu dronlardan yüksek miktarda bulunuyor. Ve bu dronlar…"
        },
        {
            "id": 101,
            "model": "뫼르소",
            "content": "Anomali'nin bulunduğu lokasyona erişimimizi engellemek için kurulmuşlar."
        },
        {
            "id": 102,
            "model": "그레고르",
            "content": "İmkanı yok. Yardım etmek için gelmiştik, yolumuzu kapatmak için…"
        },
        {
            "id": 103,
            "model": "그레고르",
            "content": "Bir nedenleri yok… değil mi…?"
        },
        {
            "id": 104,
            "content": "Now the drones have started lining up, and formed a wall as if to stop us from proceeding any farther."
        },
        {
            "id": 105,
            "model": "K사드론들",
            "teller": "Mysterious Drone",
            "title": "K Corp.",
            "content": "Merhaba, vatandaşlar. Lütfen güvenliğiniz için, on metrelik mesafesinizi koruyun."
        },
        {
            "id": 106,
            "model": "K사드론들",
            "teller": "Mysterious Drone",
            "title": "K Corp.",
            "content": "K Kuruluşu yetkilileri olaya müdahale ediyor. Güvenliğiniz emin ellerde. Lütfen on metrelik mesafenizi koruyun."
        },
        {
            "id": 107,
            "model": "히스클리프",
            "content": "Ulan, sizin elemanları am hoşafı ediyorlar, kör müsün sen?"
        },
        {
            "id": 108,
            "model": "K사드론들",
            "teller": "Mysterious Drone",
            "title": "K Corp.",
            "content": "Merhaba, vatandaşlar. Lütfen güvenliğiniz için, on metrelik mesafesinizi koruyun."
        },
        {
            "id": 109,
            "model": "이스마엘",
            "content": "Hah, talimatlar çok anlamsız. Böyle bir kargaşada on metrenin ne yararı olacak?"
        },
        {
            "id": 110,
            "model": "그레고르",
            "content": "Tç, bi' iyiliğe yanaşmayacaklar, ha…"
        },
        {
            "id": 111,
            "model": "그레고르",
            "content": "Bozuklar mı yoksa sadece kötü mü tasarlanmışlar bilmem, fakat Anomaliye ulaşana dek, bunları da aradan çıkartmamız gerekecek."
        }
    ]
}
