{
  "dataList": [
    {
      "id": "AaCfPcBe",
      "name": "Derin Yas",
      "desc": "Saldırı Sonrası 5 SP hasarı uygular.",
      "summary": "",
      "undefined": "-"
    },
    {
      "id": "AaCfPcBf",
      "name": "Bağlı Keder",
      "desc": "Belirli bir koşul altında ve 3+ Değer olduğunda, tüm Parçalar sonraki turda Sarsılır.\nZincir Parçasına 3 Kırılgan uygulandıktan sonra sona erer",
      "summary": "",
      "undefined": "-"
    },
    {
      "id": "AaCfPcBg",
      "name": "Öfke Nesnesi",
      "desc": "Kalbini Kırmış Heathcliff için öncelikli saldırı hedefi olur.\nBu birim öldüğünde, bu etki farklı bir Kişiliğe geçer.",
      "summary": "",
      "undefined": "-"
    },
    {
      "id": "AaCfPcBb",
      "name": "Uşak İşareti",
      "desc": "Belirli Saldırı Yeteneklerinin Saldırı Ağırlığını artırmak için kullanılır",
      "summary": "",
      "undefined": "-"
    },
    {
      "id": "AaCfPcBc",
      "name": "Bağlama Tekniği",
      "desc": "- Maksimum 3\n- Tur Sonu: 1 artar\n- Tur Sonu: bu etkinin Değerine eşit Bağlanma kazanılır.\n- Tur Sonu: Değer 3 ise, bu Karşılaşmanın geri kalanında Sarsılmış olur.\nSüresi dolmaz.",
      "summary": "Bir sonraki tur Değere eşit Bağlanma kazanılır.\nDeğer 3 ise, bu Karşılaşmanın geri kalanında Sarsılmış olur.",
      "undefined": "-"
    },
    {
      "id": "AaCfPcBh",
      "name": "Öldürücü Öfke",
      "desc": "Saldıran Patlayıcı Öfke etkisine sahipse, alınan hasar %100 artar",
      "undefined": "-"
    },
    {
      "id": "AaCfPcBm",
      "name": "Acı Şimşeği",
      "desc": "- Çarpışma Kazanma: Kırılan Kalp uygular ve 7 HP hasarı verir.\n- Çarpışma Kaybetme veya Rakipsiz Saldırı Sonrası: Kırılan Kalp kazanır ve 7 HP hasarı alır.\n- Yetenek sonunda 1 azalır",
      "undefined": "-"
    },
    {
      "id": "AaCfPcBn",
      "name": "Kırılan Kalp",
      "desc": "- Her Günah Türü Direnci (Değer x 0.2) kadar artar\n- Değer 3 olduğunda Sarsılır.",
      "undefined": "-"
    },
    {
      "id": "AaCfPcBp",
      "name": "Yaklaşmak İçin Cesaret",
      "desc": "- Tur Sonu: 10 SP iyileştirir\n- Her tur 3 Saldırı Gücü Artışı ve 5 Koruma kazanır\n- Saldırıldığında 5 SP iyileştirir. Sonraki tur 1 Saldırı Seviyesi Artışı kazanır (tur başına 3 kez)\n- Tur Başlangıcı: SP 0'ın altındaysa 3 Saldırı Gücü Artışı kazanır.\n- Bu Karşılaşmada hayatta kalan en az 1 müttefik varsa, Heathcliff’in HP'si 1'in altına düşmez.\nBu birimin Çekilme yetenekleri bu Karşılaşma boyunca aktif olmaz.",
      "undefined": "-"
    },
    {
      "id": "AaCfPcBo",
      "name": "Kararlılık",
      "desc": "- Tur Sonu: 10 SP iyileştirir\n- Saldırıldığında, sonraki tur 1 Saldırı Seviyesi Artışı kazanır (tur başına 3 kez)\n- Tur Başlangıcı: SP 0'ın altındaysa 3 Saldırı Gücü Artışı kazanır.\n- Bu Karşılaşmada hayatta kalan en az 1 müttefik varsa, Heathcliff’in HP'si 1'in altına düşmez.\nBu birimin Çekilme yetenekleri bu Karşılaşma boyunca aktif olmaz.",
      "undefined": "-"
    },
    {
      "id": "AaCfPcBq",
      "name": "Kırık Kalp",
      "desc": "- Maksimum Hız +2\n- Her tur 3 Hasar Artışı ve 3 Kırılgan kazanır\n- Ana hedef Heathcliff ise, Saldırı Yeteneği Son Güç +2 kazanır\n- Heathcliff'e karşı Çarpışma Kaybetme: sonraki tur 3 Bağlanma ve 3 Hasar Azalışı kazanır",
      "undefined": "-"
    },
    {
      "id": "AaCfPcBr",
      "name": "Acı İçinde Uyanması Dileği!",
      "desc": "Acı Şimşeği etkisine sahip hedeflere karşı Çarpışma Gücü -6",
      "undefined": "-"
    },
    {
      "id": "AaCfPcBi",
      "name": "Süpertermogenez",
      "desc": "Tur Sonu: Değere bağlı olarak Maksimum HP'nin %X kadar sabit hasar alır, sonra etki sona erer",
      "undefined": "-"
    },
    {
      "id": "Unobservable",
      "name": "Gözlemlenemez",
      "desc": "",
      "undefined": "-"
    },
    {
      "id": "AaCfPcBs",
      "name": "Defol Git",
      "desc": "Kalan Kalkan Değeri",
      "undefined": "-"
    }
  ]
}
