{
    "dataList": [
        {
            "id": 1001,
            "name": "Unutulmuş"
        },
        {
            "id": 1002,
            "name": "Dışlanmış"
        },
        {
            "id": 1003,
            "name": "Beş Parasız Kumarbaz"
        },
        {
            "id": 1004,
            "name": "Otomatik Fabrika"
        },
        {
            "id": 1005,
            "name": "Sevgisiz"
        },
        {
            "id": 1006,
            "name": "Çivi ve Çekiç"
        },
        {
            "id": 1007,
            "name": "İnanç ve Erozyon"
        },
        {
            "id": 1008,
            "name": "Yüzleşmeyen"
        },
        {
            "id": 1009,
            "name": "Yuva, Atölye ve Teknoloji"
        },
        {
            "id": 1010,
            "name": "Solan Çiçekler"
        },
        {
            "id": 1011,
            "name": "Hüzgün Şeyler"
        },
        {
            "id": 1012,
            "name": "Değişmeyem"
        },
        {
            "id": 1013,
            "name": "Göl Diyarı"
        },
        {
            "id": 1014,
            "name": "Sürünen Uçurum"
        },
        {
            "id": 1015,
            "name": "Kötülüğün Tanımı"
        },
        {
            "id": 1016,
            "name": "Malikanenin Kalıntıları"
        },
        {
            "id": 1017,
            "name": "Belirli bir Diyar"
        },
        {
            "id": 1101,
            "name": "Cenabet Tavuk"
        },
        {
            "id": 1102,
            "name": "D.E.N.İ.Z"
        },
        {
            "id": 1103,
            "name": "20. Eyaletteki Mucize"
        },
        {
            "id": 1104,
            "name": "Etimden Feragat Ederim, Onların Kemiklerini Almak İçin"
        },
        {
            "id": 1201,
            "name": "Kesiciler & Deliciler"
        },
        {
            "id": 1202,
            "name": "Kesilmek, yada Kesilmemek"
        },
        {
            "id": 1203,
            "name": "Delici ve Daha çok Deliciler"
        },
        {
            "id": 1204,
            "name": "Delinmek"
        },
        {
            "id": 1205,
            "name": "Kırıcılar & Darbeciler"
        },
        {
            "id": 1206,
            "name": "Parçalanmak"
        },
        {
            "id": 1301,
            "name": "Bastırılmış Öfke"
        },
        {
            "id": 1302,
            "name": "Sınırsız Öfke"
        },
        {
            "id": 1303,
            "name": "Bastırılmış Duygular"
        },
        {
            "id": 1304,
            "name": "Kontrolsüz Şehvet"
        },
        {
            "id": 1305,
            "name": "Karmaşık Şehvet"
        },
        {
            "id": 1306,
            "name": "Duygusal Ayartma"
        },
        {
            "id": 1307,
            "name": "Tekrarlayan Tembellik"
        },
        {
            "id": 1308,
            "name": "Eylemsiz Tembellik"
        },
        {
            "id": 1309,
            "name": "Duygusal Tembellik"
        },
        {
            "id": 1310,
            "name": "Yutulmuş Oburluk"
        },
        {
            "id": 1311,
            "name": "Aşırı Oburluk"
        },
        {
            "id": 1312,
            "name": "Duygusal Açlık"
        },
        {
            "id": 1313,
            "name": "Çökmüş Keder"
        },
        {
            "id": 1314,
            "name": "Batmış Keder"
        },
        {
            "id": 1315,
            "name": "Duygusal Taşkın"
        },
        {
            "id": 1316,
            "name": "Beyhude Gurur"
        },
        {
            "id": 1317,
            "name": "Zorba Gurur"
        },
        {
            "id": 1318,
            "name": "Duygusal Boyun Eğiş"
        },
        {
            "id": 1319,
            "name": "Önemsiz Kıskançlık"
        },
        {
            "id": 1320,
            "name": "Zavallı Kıskançlık"
        },
        {
            "id": 1321,
            "name": "Duygusal Yargı"
        },
        {
            "id": 1401,
            "name": "Yanan Pus"
        },
        {
            "id": 1402,
            "name": "Alev Mevsimi"
        },
        {
            "id": 1403,
            "name": "Süzülen Kanlı Sıvı"
        },
        {
            "id": 1404,
            "name": "Cesetler Dağı, Kan Denizi"
        },
        {
            "id": 1405,
            "name": "Baş Döndüren Dalgalar"
        },
        {
            "id": 1406,
            "name": "Anormal Sismik Bölge"
        },
        {
            "id": 1407,
            "name": "Ezici Dış Güç"
        },
        {
            "id": 1408,
            "name": "Amansız Kudret"
        },
        {
            "id": 1409,
            "name": "Batan Sızı"
        },
        {
            "id": 1410,
            "name": "Batan Sağanak"
        },
        {
            "id": 1411,
            "name": "Derin İç Çekiş"
        },
        {
            "id": 1412,
            "name": "Sakin Nefes"
        },
        {
            "id": 1413,
            "name": "Yükselen Güç Kaynağı"
        },
        {
            "id": 1414,
            "name": "Gök Gürültüsü ve Şimşek"
        },
        {
            "id": 1105,
            "name": "Zaman Öldüren Zaman"
        },
        {
            "id": 1106,
            "name": "WARP Ekspresinde Cinayet"
        },
        {
            "id": 1107,
            "name": "Menekşenin Öğle Vakti"
        },
        {
            "id": 1018,
            "name": "Yürek Burkan"
        },
        {
            "id": 1019,
            "name": "La Mancha Diyarı Yeniden Açılışı"
        },
        {
            "id": 1020,
            "name": "Sonsuz Şenlik"
        },
        {
            "id": 1108,
            "name": "Hat 1"
        },
        {
            "id": 1109,
            "name": "Hat 2"
        },
        {
            "id": 1110,
            "name": "Hat 3"
        },
        {
            "id": 1111,
            "name": "Hat 4 - 3. Bölüm"
        },
        {
            "id": 1112,
            "name": "Hat 4 - 4. Bölüm"
        },
        {
            "id": 1113,
            "name": "20. Eyalette Mucize"
        },
        {
            "id": 1114,
            "name": "Kurşunla Durduruldu"
        },
        {
            "id": 1115,
            "name": "LŞO Rutin Kontrol"
        },
        {
            "id": 1116,
            "name": "Etimden Feragat Ederim, Onların Kemiklerini Almak İçin BokGak"
        },
        {
            "id": 1117,
            "name": "Gece Temizliği"
        }
    ]
}
