{
  "dataList": [
    {
      "id": 1001,
      "panicName": "Zorlama",
      "lowMoraleDescription": "Tur Başlangıcı: 2 <sprite name=\"Agility\"><color=#f8c200><u><link=\"Agility\">Hızlandırma</color></link></u> and 2 <sprite name=\"Vulnerable\"><color=#e30000><u><link=\"Vulnerable\">Kırılganlık</color></link></u> kazan",
      "panicDescription": "Tur Başlangıcı: 10 HP Kaybet."
    },
    {
      "id": 1002,
      "panicName": "Outlash",
      "lowMoraleDescription": "Tur Başlangıcı: 2 <sprite name=\"Enhancement\"><color=#f8c200><u><link=\"Enhancement\">Saldırı Gücü Artışı</color></link></u> and 2 <sprite name=\"Vulnerable\"><color=#e30000><u><link=\"Vulnerable\">Kırılganlık</color></link></u> kazan",
      "panicDescription": "Tur Başlangıcı: Rastgele Müttefik 20 SP Kaybeder."
    },
    {
      "id": 1003,
      "panicName": "Bunalma",
      "lowMoraleDescription": "Tur Başlangıcı: Gain 2 <sprite name=\"Reduction\"><color=#e30000><u><link=\"Reduction\"Saldırı Gücü Düşüşü</color></link></u>",
      "panicDescription": "Bu tur birşey yapmaz."
    },
    {
      "id": 1004,
      "panicName": "Körleme",
      "lowMoraleDescription": "Tur Başlangıcı: 2 <sprite name=\"Reduction\"><color=#e30000><u><link=\"Reduction\">Saldırı Gücü Düşüşü</color></link></u> kazan",
      "panicDescription": "Tur Başlangıcı: 4 <sprite name=\"Reduction\"><color=#e30000><u><link=\"Reduction\">Saldırı Gücü Düşüşü</color></link></u> kazan"
    },
    {
      "id": 1005,
      "panicName": "Tedirgin",
      "lowMoraleDescription": "Tur Başlangıcı: 1 <sprite name=\"AttackDmgUp\"><color=#f8c200><u><link=\"AttackDmgUp\">Hasar Artışı</color></link></u> and 2 <sprite name=\"Vulnerable\"><color=#e30000><u><link=\"Vulnerable\">Kırılganlık</color></link></u> kazan",
      "panicDescription": "Tur Başlangıcı: 2 <sprite name=\"AttackDmgUp\"><color=#f8c200><u><link=\"AttackDmgUp\">Hasar Artışı</color></link></u> and 5 <sprite name=\"Vulnerable\"><color=#e30000><u><link=\"Vulnerable\">Kırılganlık</color></link></u> kazan"
    },
    {
      "id": 1006,
      "panicName": "Koşma",
      "lowMoraleDescription": "Birşey yapmaz. Vurulunca, bu kişi yetenek bitince yenilir.",
      "panicDescription": ""
    },
    {
      "id": 1007,
      "panicName": "Hüzüntü",
      "lowMoraleDescription": "Her tur 2 <sprite name=\"AttackDmgDown\"><color=#e30000><u><link=\"AttackDmgDown\">Hasar Düşüşü</color></link></u> kazan",
      "panicDescription": "Her tur 5 <sprite name=\"AttackDmgDown\"><color=#e30000><u><link=\"AttackDmgDown\">Hasar Düşüşü</color></link></u> and 2 <sprite name=\"Vulnerable\"><color=#e30000><u><link=\"Vulnerable\">Kırılganlık</color></link></u> kazan"
    },
    {
      "id": 1008,
      "panicName": "Delirmiş",
      "lowMoraleDescription": "İlk kez düşük moraldeyken, kişileri rastgele hedef alır",
      "panicDescription": "Rastgele Hedef alır; Çarpışma Gücü +1, ve 2 <sprite name=\"AttackDmgUp\"><color=#f8c200><u><link=\"AttackDmgUp\">Hasar Artışı</color></link></u> kazan"
    },
    {
      "id": 1009,
      "panicName": "İntihara Meyilli",
      "lowMoraleDescription": "İlk kez düşük moraldeyken, birşey yapamayacak hale gel",
      "panicDescription": "3 Tur birşey yapamaz. 3 tur sonra, kişi tur başı ölür; ve bütün müttefikleri her SP kayıp kondisyonu için fazladan 10 SP kaybeder"
    },
    {
      "id": 1010,
      "panicName": "Geziniyor",
      "lowMoraleDescription": "Tur Sonu: Müttefiklere 2 SP hasarı vur",
      "panicDescription": "Tur Sonu: Müttefiklere 5 SP hasarı vur. 3 tur sonra savaştan ayrılır"
    },
    {
      "id": 1011,
      "panicName": "Dengesiz",
      "lowMoraleDescription": "Tur Başlangıcı: 2 <sprite name=\"Enhancement\"><color=#f8c200><u><link=\"Enhancement\">Saldırı Gücü Artışı</color></link></u> ve 3 <sprite name=\"Binding\"><color=#e30000><u><link=\"Binding\">Yavaşlatma</color></link></u> kazan",
      "panicDescription": "Tur Başlangıcı: Sersemlenir"
    },
    {
      "id": 1012,
      "panicName": "Keyifsiz",
      "lowMoraleDescription": "Gain 1 <sprite name=\"Vulnerable\"><color=#e30000><u><link=\"Vulnerable\">Kırılganlık</color></link></u>; Bir Çatışmada, eğer herhangi bir Jeton tura gelirse, Çatışma içim Çatışma Gücü -1.",
      "panicDescription": "Gain 3 <sprite name=\"Vulnerable\"><color=#e30000><u><link=\"Vulnerable\">Kırılganlık</color></link></u>; Bir Çatışmada, eğer herhangi bir Jeton tura gelirse, Çatışma içim Çatışma Gücü -3."
    },
    {
      "id": 9999,
      "panicName": "Panik",
      "lowMoraleDescription": "",
      "panicDescription": "Bu tur birşey yapmaz."
    },
    {
      "id": 1013,
      "panicName": "Safsızlık",
      "lowMoraleDescription": "1 <sprite name=\"Vulnerable\"><color=#e30000><u><link=\"Vulnerable\">Kırılganlık</color></link></u> kazan. Bu kişi çatışmayı kaybeder ise hedef 2 SP Kaybeder",
      "panicDescription": "1 <sprite name=\"Vulnerable\"><color=#e30000><u><link=\"Vulnerable\">Kırılganlık</color></link></u> kazan. Bu kişi çatışmayı kaybeder ise hedef 5 SP Kaybeder"
    },
    {
      "id": 1014,
      "panicName": "İntikam",
      "lowMoraleDescription": "Tur Başlangıcı: 1 <sprite name=\"Enhancement\"><color=#f8c200><u><link=\"Enhancement\">Saldırı Gücü Artışı</color></link></u> ve 3 <sprite name=\"DefenseDown\"><color=#e30000><u><link=\"DefenseDown\">Savunma Seviyesi Düşüşü</color></link></u> kazan. Son tur alınan hasara göre <sprite name=\"AttackDmgUp\"><color=#f8c200><u><link=\"AttackDmgUp\">Hasar Artışı</color></link></u> kazan (Azami canın kaybedilen her 3%ü için 1 <sprite name=\"AttackDmgUp\"><color=#f8c200><u><link=\"AttackDmgUp\">Hasar Artışı</color></link></u> kazan)",
      "panicDescription": "Tur Başlangıcı: 2 <sprite name=\"Enhancement\"><color=#f8c200><u><link=\"Enhancement\">Saldırı Gücü Artışı</color></link></u> ve 6 <sprite name=\"DefenseDown\"><color=#e30000><u><link=\"DefenseDown\">Savunma Seviyesi Düşüşü</color></link></u> kazan. Son tur alınan hasara göre <sprite name=\"AttackDmgUp\"><color=#f8c200><u><link=\"AttackDmgUp\">Hasar Artışı</color></link></u> kazan (Azami canın kaybedilen her 3%ü için 1 <sprite name=\"AttackDmgUp\"><color=#f8c200><u><link=\"AttackDmgUp\">Hasar Artışı</color></link></u> kazan)"
    },
    {
      "id": 1015,
      "panicName": "Solgun Panik",
      "lowMoraleDescription": "[MentalSystemResultDecrease_Typo] +2",
      "panicDescription": "Her Tur Sonu: 2 <sprite name=\"Binding\"><color=#f8c200><u><link=\"Binding\">Yavaşlatma</color></link></u> kazan.\nBu kişinin her çevirdiği Jeton Tura olur."
    },
    {
      "id": 1016,
      "panicName": "Kin",
      "lowMoraleDescription": "Tur Başlangıcı: 2 [AttackDmgUp] ve 3 [DefenseDown] kazan",
      "panicDescription": "Tur Başlangıcı: 1 [Enhancement] ve 5 [DefenseDown] kazan"
    },
    {
      "id": 1026,
      "panicName": "Yıkım",
      "lowMoraleDescription": "Her Tur Sonu 3 [Sinking] kazan; Jeton G]c] -1",
      "panicDescription": "Her Tur sonu 5 [Sinking] ve +3 [Sinking] Miktarı kazan; Çatışma Gücü -2"
    }
  ]
}
